msac/__init__.py
msac/calculate_adduct_mz.py
msac/calculate_input_mz.py
msac/check.py
msac/cli.py
msac/example_data/Example_script.ipynb
msac/example_data/adduct_list_full.csv
msac/example_data/adduct_only_list.csv
msac/example_data/example_inputs.csv
msac/process.py
msac-0.1.2.dist-info/LICENSE.txt
msac-0.1.2.dist-info/METADATA
msac-0.1.2.dist-info/WHEEL
msac-0.1.2.dist-info/entry_points.txt
msac-0.1.2.dist-info/RECORD
