Metadata-Version: 2.3
Name: msac
Version: 0.1.2
Summary: Molecular Spectrometry Adduct Calculator: Calculates m/z of potential adducts given compound m/z
License: LICENSE.txt
Author: Madison Blumer
Author-email: madison.blumer@pnnl.gov
Requires-Python: >=3.9,<4.0
Classifier: License :: Other/Proprietary License
Classifier: Programming Language :: Python :: 3
Classifier: Programming Language :: Python :: 3.9
Classifier: Programming Language :: Python :: 3.10
Classifier: Programming Language :: Python :: 3.11
Classifier: Programming Language :: Python :: 3.12
Classifier: Programming Language :: Python :: 3.13
Requires-Dist: jupyter (>=1.0.0,<2.0.0)
Requires-Dist: molmass (>=2023.8.30,<2024.0.0)
Requires-Dist: numpy (>=1.26.1,<2.0.0)
Requires-Dist: pandas (>=2.1.1,<3.0.0)
